MANIFEST.in
setup.cfg
setup.py
gat_games/__init__.py
gat_games.egg-info/PKG-INFO
gat_games.egg-info/SOURCES.txt
gat_games.egg-info/dependency_links.txt
gat_games.egg-info/requires.txt
gat_games.egg-info/top_level.txt
gat_games/game_engine/__init__.py
gat_games/game_engine/cardgame.py
gat_games/game_engine/engine.py
gat_games/game_engine/gat_json.py
gat_games/games/__game_model__.py
gat_games/games/__init__.py
gat_games/games/backgammon.py
gat_games/games/blackjack.py
gat_games/games/checkers.py
gat_games/games/chess.py
gat_games/games/hole.py
gat_games/games/poker_texasholdem.py
gat_games/games/tranca.py
gat_games/games/truco.py
gat_games/games/truco_clean_deck.py
gat_games/games/truco_gaucho.py
tests/__init__.py
tests/test_init.py
tests/game_engine/__init__.py
tests/game_engine/test_cardgame.py
tests/game_engine/test_engine.py
tests/game_engine/test_gat_json.py
tests/games/__init__.py
tests/games/test_truco.py