Metadata-Version: 1.1
Name: gat-games
Version: 0.0.2
Summary: GAT Games
Home-page: https://github.com/gatournament/gat-games
Author: gatournament
Author-email: info@gatournament.com
License: MIT
Keywords: gat game algorithms tournament
Platform: UNKNOWN
Classifier: Operating System :: OS Independent
Classifier: Topic :: Software Development
